pytagsup/__init__.py
pytagsup/attribute.py
pytagsup/html.py
pytagsup/tags.py
pytagsup-0.1.dist-info/LICENSE
pytagsup-0.1.dist-info/METADATA
pytagsup-0.1.dist-info/WHEEL
pytagsup-0.1.dist-info/top_level.txt
pytagsup-0.1.dist-info/RECORD
