Metadata-Version: 2.1
Name: pytagsup
Version: 0.1
Summary: PyTags is a small XML/HTML construction templating library for Python, inspired by JavaTags. 
Author-email: Manlio Modugno <manliomodugno@gmail.com>
License: MIT License
Project-URL: Homepage, https://github.com/manlioGit/pytagsup
Keywords: tags,html,templating
Classifier: Programming Language :: Python :: 3
Classifier: License :: OSI Approved :: MIT License
Classifier: Operating System :: OS Independent
Requires-Python: >=3.11
License-File: LICENSE
Provides-Extra: test
Requires-Dist: pytest ; extra == 'test'
